egypt/__init__.py
egypt/pyramid.py
old/__init__.py
old/fusion.py
old/new_pyramid.py
old/plot.py
old/pyramid.py
old/source.py
old/test.py
pyramid/__init__.py
pyramid/pyramid.py
egypt-0.0.2.dist-info/METADATA
egypt-0.0.2.dist-info/WHEEL
egypt-0.0.2.dist-info/top_level.txt
egypt-0.0.2.dist-info/RECORD
